lsq_mcp_server/__init__.py
lsq_mcp_server-0.1.0.dist-info/METADATA
lsq_mcp_server-0.1.0.dist-info/WHEEL
lsq_mcp_server-0.1.0.dist-info/entry_points.txt
lsq_mcp_server-0.1.0.dist-info/RECORD
