Metadata-Version: 2.4
Name: lsq-mcp-server
Version: 0.1.0
Summary: Add your description here
Author: 刘松奇
Requires-Python: >=3.11
Requires-Dist: mcp[cli]>=1.10.1
